ssh2/__init__.pxd
ssh2/__init__.py
ssh2/_version.py
ssh2/agent.cp310-win_amd64.pyd
ssh2/agent.pxd
ssh2/c_pkey.pxd
ssh2/c_sftp.pxd
ssh2/c_ssh2.pxd
ssh2/c_stat.pxd
ssh2/channel.cp310-win_amd64.pyd
ssh2/channel.pxd
ssh2/error_codes.cp310-win_amd64.pyd
ssh2/error_codes.pxd
ssh2/exceptions.cp310-win_amd64.pyd
ssh2/fileinfo.cp310-win_amd64.pyd
ssh2/fileinfo.pxd
ssh2/knownhost.cp310-win_amd64.pyd
ssh2/knownhost.pxd
ssh2/libcrypto-3-x64.dll
ssh2/libssl-3-x64.dll
ssh2/listener.cp310-win_amd64.pyd
ssh2/listener.pxd
ssh2/msvcr120.dll
ssh2/pkey.cp310-win_amd64.pyd
ssh2/pkey.pxd
ssh2/publickey.cp310-win_amd64.pyd
ssh2/publickey.pxd
ssh2/session.cp310-win_amd64.pyd
ssh2/session.pxd
ssh2/sftp.cp310-win_amd64.pyd
ssh2/sftp.pxd
ssh2/sftp_handle.cp310-win_amd64.pyd
ssh2/sftp_handle.pxd
ssh2/statinfo.cp310-win_amd64.pyd
ssh2/statinfo.pxd
ssh2/utils.cp310-win_amd64.pyd
ssh2/utils.pxd
ssh2/vcruntime140.dll
ssh2_python-1.2.0.post1.dist-info/licenses/COPYING
ssh2_python-1.2.0.post1.dist-info/licenses/LICENSE
ssh2_python-1.2.0.post1.dist-info/METADATA
ssh2_python-1.2.0.post1.dist-info/WHEEL
ssh2_python-1.2.0.post1.dist-info/top_level.txt
ssh2_python-1.2.0.post1.dist-info/RECORD
